akaba.py
akaba-1.0.1.dist-info/LICENSE
akaba-1.0.1.dist-info/METADATA
akaba-1.0.1.dist-info/WHEEL
akaba-1.0.1.dist-info/entry_points.txt
akaba-1.0.1.dist-info/top_level.txt
akaba-1.0.1.dist-info/RECORD
