Metadata-Version: 2.1
Name: akaba
Version: 1.0.1
Summary: This is a CLI scaffolding tool for FastAPI. It helps create a project structure template with boilerplate code
License-File: LICENSE
Requires-Dist: Click
Requires-Dist: pydantic-settings
Requires-Dist: FastAPI
Requires-Dist: SQLAlchemy
Requires-Dist: alembic
Requires-Dist: pydantic
